{
  "assets": [
      {
        "enabled": true,
        "symbol": "AVAX",
        "support": 30,
        "resistance": 37,
        "entry": 34,
        "shares": 2,
        "buy_limit_3": 0,
        "buy_limit_2": 0,
        "buy_limit_1": 0,
        "sell_limit_1": 37,
        "sell_limit_2": 39.5,
        "sell_limit_3": 0
      },
      {
        "enabled": false,
        "symbol": "DOT",
        "support": 4.20,
        "resistance": 4.6,
        "entry": 0,
        "shares": 0,
        "buy_limit_3": 0,
        "buy_limit_2": 0,
        "buy_limit_1": 0,
        "sell_limit_1": 4.6,
        "sell_limit_2": 0,
        "sell_limit_3": 0
      }
    ]
}
